enviopack/Enviopack.py
enviopack/__init__.py
enviopack/constants.py
enviopack/Auth/Auth.py
enviopack/Auth/__init__.py
enviopack/Orders/Orders.py
enviopack/Orders/__init__.py
enviopack/Pickings/Pickings.py
enviopack/Pickings/__init__.py
enviopack/Quote/Quote.py
enviopack/Quote/__init__.py
enviopack-0.3.0.dist-info/LICENSE
enviopack-0.3.0.dist-info/METADATA
enviopack-0.3.0.dist-info/WHEEL
enviopack-0.3.0.dist-info/top_level.txt
enviopack-0.3.0.dist-info/RECORD
